odoo/addons/partner_property/README.rst
odoo/addons/partner_property/__init__.py
odoo/addons/partner_property/__manifest__.py
odoo/addons/partner_property/i18n/es.po
odoo/addons/partner_property/i18n/it.po
odoo/addons/partner_property/i18n/partner_property.pot
odoo/addons/partner_property/models/__init__.py
odoo/addons/partner_property/models/res_company.py
odoo/addons/partner_property/models/res_partner.py
odoo/addons/partner_property/readme/CONTRIBUTORS.md
odoo/addons/partner_property/readme/DESCRIPTION.md
odoo/addons/partner_property/readme/ROADMAP.md
odoo/addons/partner_property/readme/USAGE.md
odoo/addons/partner_property/static/description/icon.png
odoo/addons/partner_property/static/description/index.html
odoo/addons/partner_property/tests/__init__.py
odoo/addons/partner_property/tests/test_export.py
odoo/addons/partner_property/tests/test_res_partner.py
odoo/addons/partner_property/views/res_partner_views.xml
odoo_addon_partner_property-18.0.1.0.2.dist-info/METADATA
odoo_addon_partner_property-18.0.1.0.2.dist-info/WHEEL
odoo_addon_partner_property-18.0.1.0.2.dist-info/top_level.txt
odoo_addon_partner_property-18.0.1.0.2.dist-info/RECORD
